LICENSE
MANIFEST.in
README.rst
setup.py
django_banana/__init__.py
django_banana/experiment.py
django_banana/keying.py
django_banana/manager.py
django_banana/middleware.py
django_banana/models.py
django_banana/option.py
django_banana.egg-info/PKG-INFO
django_banana.egg-info/SOURCES.txt
django_banana.egg-info/dependency_links.txt
django_banana.egg-info/requires.txt
django_banana.egg-info/top_level.txt
django_banana.egg-info/zip-safe