Metadata-Version: 1.1
Name: django-banana
Version: 1.0.0
Summary: Delicious split testing for Django 1.6+
Home-page: http://bruun.co/
Author: Nick Bruun
Author-email: nick@bruun.co
License: Copyright (c) Nick Bruun <nick@bruun.co>
